<annotation>
	<folder>entrenamiento</folder>
	<filename>images21.jpg</filename>
	<path>C:\Users\TestHost\Pictures\entrenamiento\images21.jpg</path>
	<source>
		<database>Unknown</database>
	</source>
	<size>
		<width>262</width>
		<height>192</height>
		<depth>3</depth>
	</size>
	<segmented>0</segmented>
	<object>
		<name>feliz</name>
		<pose>Unspecified</pose>
		<truncated>0</truncated>
		<difficult>0</difficult>
		<bndbox>
			<xmin>124</xmin>
			<ymin>64</ymin>
			<xmax>203</xmax>
			<ymax>136</ymax>
		</bndbox>
	</object>
	<object>
		<name>feliz</name>
		<pose>Unspecified</pose>
		<truncated>0</truncated>
		<difficult>0</difficult>
		<bndbox>
			<xmin>85</xmin>
			<ymin>35</ymin>
			<xmax>232</xmax>
			<ymax>159</ymax>
		</bndbox>
	</object>
</annotation>
